shipyard_census/__init__.py
shipyard_census/census.py
shipyard_census/cli/__init__.py
shipyard_census/cli/authtest.py
shipyard_census/cli/trigger_sync_cli.py
shipyard_census-0.2.0.dist-info/METADATA
shipyard_census-0.2.0.dist-info/WHEEL
shipyard_census-0.2.0.dist-info/RECORD
