Metadata-Version: 2.1
Name: shipyard-census
Version: 0.2.0
Summary: A local client for connecting and working with Census
License: Apache 2.0
Author: JR
Author-email: johnathan.rodriguez@shipyardapp.com
Requires-Python: >=3.9,<4.0
Classifier: License :: Other/Proprietary License
Classifier: Programming Language :: Python :: 3
Classifier: Programming Language :: Python :: 3.9
Classifier: Programming Language :: Python :: 3.10
Classifier: Programming Language :: Python :: 3.11
Requires-Dist: requests (==2.31.0)
Requires-Dist: shipyard-bp-utils (>=1.2.1,<2.0.0)
Requires-Dist: shipyard-templates (>=0.8.2,<0.9.0)
